betterproto/__init__.py
betterproto/_types.py
betterproto/_version.py
betterproto/casing.py
betterproto/compile/__init__.py
betterproto/compile/importing.py
betterproto/compile/naming.py
betterproto/enum.py
betterproto/grpc/__init__.py
betterproto/grpc/grpclib_client.py
betterproto/grpc/grpclib_server.py
betterproto/grpc/util/__init__.py
betterproto/grpc/util/async_channel.py
betterproto/lib/__init__.py
betterproto/lib/google/__init__.py
betterproto/lib/google/protobuf/__init__.py
betterproto/lib/google/protobuf/compiler/__init__.py
betterproto/lib/pydantic/__init__.py
betterproto/lib/pydantic/google/__init__.py
betterproto/lib/pydantic/google/protobuf/__init__.py
betterproto/lib/pydantic/google/protobuf/compiler/__init__.py
betterproto/lib/std/__init__.py
betterproto/lib/std/google/__init__.py
betterproto/lib/std/google/protobuf/__init__.py
betterproto/lib/std/google/protobuf/compiler/__init__.py
betterproto/plugin/__init__.py
betterproto/plugin/__main__.py
betterproto/plugin/compiler.py
betterproto/plugin/main.py
betterproto/plugin/models.py
betterproto/plugin/module_validation.py
betterproto/plugin/parser.py
betterproto/plugin/plugin.bat
betterproto/plugin/typing_compiler.py
betterproto/py.typed
betterproto/templates/header.py.j2
betterproto/templates/template.py.j2
betterproto/utils.py
betterproto_fw-2.0.2.dist-info/METADATA
betterproto_fw-2.0.2.dist-info/WHEEL
betterproto_fw-2.0.2.dist-info/entry_points.txt
betterproto_fw-2.0.2.dist-info/licenses/LICENSE.md
betterproto_fw-2.0.2.dist-info/RECORD
