Metadata-Version: 2.4
Name: betterproto-fw
Version: 2.0.2
Summary: A better Protobuf / gRPC generator & library
Keywords: protobuf,gRPC
Author-Email: "Daniel G. Taylor" <danielgtaylor@gmail.com>
License-Expression: MIT
Requires-Python: >=3.9
Requires-Dist: grpclib<0.5.0,>=0.4.1
Requires-Dist: python-dateutil<3.0.0,>=2.8.0
Requires-Dist: typing-extensions<5.0.0,>=4.7.1
Provides-Extra: compiler
Requires-Dist: ruff~=0.9.1; extra == "compiler"
Requires-Dist: jinja2>=3.0.3; extra == "compiler"
Provides-Extra: rust-codec
Requires-Dist: betterproto-rust-codec==0.1.1; extra == "rust-codec"
